{"0": {"Well": {"0": "A12", "1": "C01", "2": "D01", "3": "G10", "4": "H08", "5": "A09", "6": "A12", "7": "G04", "8": "A12", "9": "E02"}, "Unnamed: 0": {"0": NaN, "1": NaN, "2": NaN, "3": NaN, "4": NaN, "5": NaN, "6": NaN, "7": NaN, "8": NaN, "9": NaN}, "Sample": {"0": NaN, "1": NaN, "2": NaN, "3": NaN, "4": NaN, "5": NaN, "6": NaN, "7": NaN, "8": NaN, "9": NaN}, "Content": {"0": "Pos Ctrl", "1": "Unkn-03", "2": "Unkn-04", "3": "Unkn-79", "4": "Unkn-64", "5": "Unkn-65", "6": "Pos Ctrl", "7": "Unkn-31", "8": "Pos Ctrl", "9": "Unkn-13"}, "Peak Height": {"0": 386.969316712648, "1": 311.520326367313, "2": 295.844563805826, "3": 285.189678475179, "4": 1069.01650097804, "5": 286.780221358199, "6": 132.255065444348, "7": 337.337658016976, "8": 295.004213186711, "9": 911.108700649051}, "Well Note": {"0": NaN, "1": NaN, "2": NaN, "3": NaN, "4": NaN, "5": NaN, "6": NaN, "7": NaN, "8": NaN, "9": NaN}, "Target": {"0": NaN, "1": NaN, "2": NaN, "3": NaN, "4": NaN, "5": NaN, "6": NaN, "7": NaN, "8": NaN, "9": NaN}, "Begin Temperature": {"0": 59.5, "1": 57.5, "2": 60.0, "3": 57.5, "4": 60.0, "5": 61.0, "6": 61.5, "7": 61.5, "8": 62.0, "9": 60.5}, "Fluor": {"0": "Quasar 670", "1": "Quasar 670", "2": "Quasar 670", "3": "Quasar 670", "4": "FAM", "5": "HEX", "6": "HEX", "7": "HEX", "8": "Cal Red 610", "9": "Cal Red 610"}, "End Temperature": {"0": 78.5, "1": 84.0, "2": 84.0, "3": 71.5, "4": 72.5, "5": 68.0, "6": 67.0, "7": 68.0, "8": 67.5, "9": 69.0}, "Melt Temperature": {"0": 66.0, "1": 65.5, "2": 65.5, "3": 65.5, "4": 66.5, "5": 64.5, "6": 64.0, "7": 64.5, "8": 64.5, "9": 64.5}}}